es_sync/__init__.py
py_mysql_elasticsearch_sync-0.3.3.2.dist-info/DESCRIPTION.rst
py_mysql_elasticsearch_sync-0.3.3.2.dist-info/METADATA
py_mysql_elasticsearch_sync-0.3.3.2.dist-info/RECORD
py_mysql_elasticsearch_sync-0.3.3.2.dist-info/WHEEL
py_mysql_elasticsearch_sync-0.3.3.2.dist-info/entry_points.txt
py_mysql_elasticsearch_sync-0.3.3.2.dist-info/metadata.json
py_mysql_elasticsearch_sync-0.3.3.2.dist-info/top_level.txt
src/__init__.py
src/sample.yaml
