Metadata-Version: 2.0
Name: py-mysql-elasticsearch-sync
Version: 0.3.3.2
Summary: MySQL to Elasticsearch sync tool
Home-page: https://github.com/zhongbiaodev/py-mysql-elasticsearch-sync
Author: Windfarer
Author-email: windfarer@gmail.com
License: MIT
Platform: UNKNOWN
Requires-Dist: PyMySQL (==0.6.7)
Requires-Dist: PyYAML (==3.11)
Requires-Dist: future (==0.15.2)
Requires-Dist: lxml (==3.5.0)
Requires-Dist: mysql-replication (==0.8)
Requires-Dist: requests (==2.9.1)
